lochnest_monster/__init__.py
lochnest_monster/basic_sampler.py
lochnest_monster/box_sampler.py
lochnest_monster/combined_sampler.py
lochnest_monster/ellipsoid_sampler.py
lochnest_monster/nball_sampler.py
lochnest_monster/nbox_sampler.py
lochnest_monster/bounds/__init__.py
lochnest_monster/bounds/box.py
lochnest_monster/bounds/combined.py
lochnest_monster/bounds/ellipsoid.py
lochnest_monster/bounds/nballs.py
lochnest_monster/bounds/nboxes.py
lochnest_monster-0.1.2.dist-info/METADATA
lochnest_monster-0.1.2.dist-info/RECORD
lochnest_monster-0.1.2.dist-info/WHEEL
lochnest_monster-0.1.2.dist-info/top_level.txt
