Metadata-Version: 2.1
Name: lochnest-monster
Version: 0.1.2
Summary: An ancient and mysterious nested sampling algorithm
Home-page: https://github.com/ACCarnall/lochnest_monster
Author: Adam Carnall
Author-email: adamc@roe.ac.uk
License: UNKNOWN
Project-URL: GitHub, https://github.com/ACCarnall/lochnest_monster
Platform: UNKNOWN
Requires-Dist: numpy (>=1.14.2)
Requires-Dist: matplotlib (>=2.2.2)
Requires-Dist: scipy
Requires-Dist: sklearn
